colrag/__init__.py
colrag/cli.py
colrag/config.py
colrag/indexer.py
colrag/logger.py
colrag/plugins/__init__.py
colrag/plugins/base.py
colrag/retriever.py
colrag/utils.py
colrag-0.2.1.dist-info/LICENCE
colrag-0.2.1.dist-info/METADATA
colrag-0.2.1.dist-info/WHEEL
colrag-0.2.1.dist-info/entry_points.txt
colrag-0.2.1.dist-info/RECORD
