Metadata-Version: 2.1
Name: colrag
Version: 0.2.1
Summary: A RAG pipeline using ColBERT via RAGatouille
Home-page: https://syedzaidi-kiwi.github.io/
License: MIT
Author: Syed Asad
Author-email: syed.asad@kiwitech.com
Requires-Python: >=3.9,<4.0
Classifier: License :: OSI Approved :: MIT License
Classifier: Programming Language :: Python :: 3
Classifier: Programming Language :: Python :: 3.9
Classifier: Programming Language :: Python :: 3.10
Classifier: Programming Language :: Python :: 3.11
Classifier: Programming Language :: Python :: 3.12
Requires-Dist: PyPDF2 (>=2.0.0,<3.0.0)
Requires-Dist: beautifulsoup4 (>=4.10.0,<5.0.0)
Requires-Dist: openpyxl (>=3.0.7,<4.0.0)
Requires-Dist: pandas (>=1.3.0,<2.0.0)
Requires-Dist: pydantic (>=1.8.2,<2.0.0)
Requires-Dist: pytest-cov (>=2.12.1,<3.0.0)
Requires-Dist: python-docx (>=0.8.11,<0.9.0)
Requires-Dist: python-dotenv (>=0.19.0,<0.20.0)
Requires-Dist: ragatouille (==0.0.8.post2)
Requires-Dist: rich (>=10.12.0,<11.0.0)
Requires-Dist: tqdm (>=4.62.3,<5.0.0)
Requires-Dist: typer (>=0.4.0,<0.5.0)
Project-URL: Documentation, https://github.com/syedzaidi-kiwi/ColRAG/blob/main/README.md
Project-URL: Repository, https://github.com/syedzaidi-kiwi/ColRAG.git
